{
	"Meta(Acqusition)": {
		"doc_id": "REPORT-news_r-14903",
		"doc_category": "REPORT",
		"doc_type": "news_r",
		"doc_name": "재난지원금 '약발' 안먹히는 지역, 서울엔 딱 네군데 있다",
		"author": "손해용",
		"publisher": "중앙일보",
		"publisher_year": "2020",
		"doc_origin": "중앙일보"
	},
	"Meta(Refine)": {
		"passage_id": "REPORT-news_r-14903-00001",
		"passage": "신종 코로나바이러스 감염증(코로나19) 사태로 주저앉았던 자영업자들의 매출이 평균적으로 지난해 수준을 회복한 것으로 조사됐다.\n  사회적 거리두기가 완화되고, 정부·지방자치단체가 지원한 긴급재난지원금의 효과로 분석된다.\n  그러나 신학기 특수가 실종된 대학가와 관광객·유동인구·고령층 등을 중심으로 수요가 형성된 상권의 매출은 여전히 부진을 벗어나지 못했다.\n  전국 66만 소상공인 사업장의 각종 결제 정보를 관리하는 ‘한국신용데이터’와 중앙일보가 함께 서울 시내 425개 동(洞) 주요 점포의 신용카드 매출(이하 매출)을 분석한 결과다.\n   이에 따르면 서울 소상공인 점포의 매출은 5월 마지막 주(5월 25~31일) 기준으로 지난해 같은 기간 대비 0.\n 97을 기록했다.\n  지난해 가게에서 100개를 팔았다면 올해에는 평균적으로 97개를 팔았다는 얘기다.\n  소상공인의 매출은 코로나19 국내 첫 확진자가 발생한 1월 다섯째 주(1월 27일~2월 2일)부터 2월 넷째 주(2월 24일~3월 1일)까지 전년 대비 계속 감소했다.\n  그러나 코로나19의 확산이 주춤해진 3월부터 서서히 감소세가 완화하더니, 연휴가 이어지고, 긴급재난지원금이 풀린 5월부터 회복세가 가팔라졌다.\n   매출 회복을 견인한 곳은 이른바 동네상권이다.\n  은평구 증산동, 성북구 장위동·석관동, 강서구 염창동, 강남구 개포동, 송파구 가락동·마천동 등은 5월 마지막 주 1.\n 2 이상의 매출을 기록했다.\n  지난해보다 매출이 20% 이상 늘었다는 얘기다.\n  김동호 한국신용데이터 대표는 “대규모 아파트 단지나 주택가가 밀집한 ‘베드타운’으로 꼽히는 곳의 매출 증가가 두드러진다”며 “감염 우려로 소비자들이 사람이 많이 모이는 대형 상권이나 회사 근처보다는 집에서 가까운 동네 점포를 이용한 것으로 분석된다”고 말했다.\n   하지만 29개 동은 코로나19 발생 약 4달이 지나도 지난해 매출의 90% 수준을 회복하지 못하고 있다.\n  크게 ▶대학가 ▶관광 상권 ▶환승역 ▶시니어 거리로 분류된다.\n  긴급재난지원금과 거리두기 완화에 따른 혜택을 받지 못한 ‘사각지대’인 셈이다.\n   지난해의 61% 수준의 매출을 기록하고 있는 청파동2가(숙명여대)를 비롯해 서교동(홍익대)·화양동(건국대) 등  대학 캠퍼스 주변 11개 동의 타격이 두드러진다.\n  학사 일정이 취소·연기되면서 3월 신학기부터 상권은 초토화됐고, 각종 행사와 모임까지 사라지며 지금까지 장사를 망치고 있다.\n ",
		"passage_Cnt": 1211
	},
	"Annotation": {
		"summary1": "코로나19로 주저앉았던 자영업자들의 매출이 회복되었지만 대학가와 관광객·유동인구·고령층 중심으로 수요가 형성된 상권의 매출은 여전히 부진하다.",
		"summary2": "신종 코로나바이러스 감염증(코로나19) 사태로 주저앉았던 자영업자들의 매출이 평균적으로 지난해 수준을 회복한 것으로 조사됐다. 그러나 신학기 특수가 실종된 대학가와 관광객·유동인구·고령층 등을 중심으로 수요가 형성된 상권의 매출은 여전히 부진을 벗어나지 못했다.",
		"summary3": null,
		"summary_3_cnt": null
	}
}