{
	"Meta(Acqusition)": {
		"doc_id": "REPORT-news_r-25972",
		"doc_category": "REPORT",
		"doc_type": "news_r",
		"doc_name": "[단독] 매니저 없이 한국행…유연석과 로맨스 찍는 본드걸 스타",
		"author": "나원정",
		"publisher": "중앙일보",
		"publisher_year": "2020",
		"doc_origin": "중앙일보"
	},
	"Meta(Refine)": {
		"passage_id": "REPORT-news_r-25972-00002",
		"passage": " 특히 유연석은 극중 그와 로맨스도 나눈다.\n  쿠릴렌코는 “유연석과 호흡은 멋지다.\n  우린 영어로 의사소통하는데 그는 무척 친절하고 또 놀라운 배우”라 했다.\n  전날 유연석이 공연하는 뮤지컬 ‘베르테르’를 다같이 봤는데 “음악, 감정연기 덕분에 한국어를 몰라도 내용이 이해됐다.\n  공연가이자, 가수, 뮤지컬 배우, 무대 배우로서 그의 완전히 다른 면모를 보게 됐다”면서다.\n    영·불·러 3개국어…첫 한국말? 감사합니다우크라이나에서 우크라이나인 아버지, 러시아인 어머니 슬하에서 태어난 그는 13살에 모스크바에서 모델로 발탁돼 파리에서 모델활동을 이어가며 프랑스어‧러시아어‧영어 3개국어에 능하다.\n  이탈리아어‧스페인어 등도 간단한 대화는 가능하단다.\n  ‘고요한 아침’ 현장에서 한국어를 귀동냥하며 배운 말? “지금으로선 ‘캄사합니다’뿐이죠.\n ”(웃음)  하지만 “한국 사람끼리 무슨 얘기하는지 알아들을 때가 있다”고 했다.\n  “이런 말 한 거 아냐? 그러면 어떻게 알았냐고 놀라더군요.\n  관찰력이 좋은 편이라 사람들이 말하는 방식, 표정, 몸동작을 보죠.\n  (배우로서) 전 세계를 돌아다니며 살다보니 익힌 기술이죠.\n ” 코로나 확진, 저를 멈추고 삶 돌아보게 했죠바쁘게 돌아가던 그의 삶은 올 3월 코로나19로 인해 한순간 멈춰섰다.\n  회복한 지금 코로나19의 경험을 묻자 그는 가만히 “처음엔 무서웠다”고 돌이켰다.\n  “너무 많은 다른 얘기들을 듣게 되잖아요.\n  운 좋게도 저는 호흡기 증세가 없었고 일주일간 고열에 시달린 후엔 괜찮았어요.\n ”   그러면서 “올해는 전체가 이상했다.\n  모든 게 멈췄다.\n  그런데 이런 말이 이상할 수 있지만, 코로나19가 나쁜 것만은 아니었다”며 말을 이었다.\n  제 삶의 속도를 줄이고 저를 멈춰 세웠잖아요.\n  덕분에 지금까지 인생과 현재의 삶을 돌아보게 됐어요.\n  지구상 어떤 것도 영원하지 않다는 걸 깨달았죠.\n  모든 가치와 관계를 되돌아보게 됐어요.\n  인생의 더 중요한 것들에 눈뜨게 해줬어요.\n  우린 모두 속도를 줄일 필요가 있잖아요.\n  물론 매우 힘겹고, 슬픈 시기지만요.\n ” 지금도 코로나19에 시달리는 이들에겐 “여기 있는 저를 보고 용기 내달라” 면서 ”우린 강하게 버텨야 한다” 했다.\n  “가장 중요한 건 건강을 지키는 것이다.\n  건강할수록 병이 와도 잘 싸울 수 있다”고 강조하며 K방역에 대한 감탄도 내비쳤다.\n  “다른 나라들은 아무것도 제 기능을 못하고 있는데 한국에 와선 모처럼 기대도 못했던 문화적인 저녁시간(뮤지컬 ‘베르테르’ 관람)을 보낼 수 있었다.\n ",
		"passage_Cnt": 1273
	},
	"Annotation": {
		"summary1": "베르테르를 본 쿠릴렌코가 뮤지컬 베르테르를 보고 배우가 무척 친절하고 감정 연기를 잘한다고 감상 소감을 전했다. ",
		"summary2": "쿠릴렌코는 “유연석과 호흡은 멋지다. 우린 영어로 의사소통하는데 그는 무척 친절하고 또 놀라운 배우”라 했다. 전날 유연석이 공연하는 뮤지컬 ‘베르테르’를 다같이 봤는데 “음악, 감정연기 덕분에 한국어를 몰라도 내용이 이해됐다.",
		"summary3": null,
		"summary_3_cnt": null
	}
}