{
	"Meta(Acqusition)": {
		"doc_id": "REPORT-news_r-24343",
		"doc_category": "REPORT",
		"doc_type": "news_r",
		"doc_name": "英나이트클럽 초토화되자, 무너진 업종은 미용실·택시였다",
		"author": "이민정",
		"publisher": "중앙일보",
		"publisher_year": "2020",
		"doc_origin": "중앙일보"
	},
	"Meta(Refine)": {
		"passage_id": "REPORT-news_r-24343-00001",
		"passage": "영국에서 신종 코로나바이러스 감염증(코로나19) 2차 확산이 이어지고 있는 가운데 나이트클럽 60% 이상이 2개월 이내 파산할 위기에 놓였다고 파이낸션타임스(FT)가 19일 (현지시간) 보도했다.\n  코로나19 확산을 막기 위해 6개월간 이어진 봉쇄조치가 직격탄이 됐다는 분석이다.\n  영국 최대 규모의 나이트클럽 기업인 델틱 그룹(Deltic Group)은 지난주 400명 직원을 해고하는 등 사업 규모를 대폭 축소하고 있다.\n  델틱 그룹은 영국 전역에서 54개 클럽을 운영하고 있다.\n  델틱 그룹 최고경영자(CEO)인 피터 막스는 “코로나19로 인한 심야 통금 조치가 계속되고, 정부의 추가 재정 지원이 없다면 상당수의 지점은 11월까지 버티기 힘들 것”이라고 말했다.\n  막스 CEO는 현 상황이 유지될 경우 다음 달 1000명의 직원을 추가 해고할 수 있다고 밝혔다.\n  영국의 유흥업은 코로나19로 인한 경제적 타격이 유독 컸다.\n  지난 6월부터 단계적으로 이뤄진 봉쇄 해제 대상에서 빠진 탓이다.\n  영국 정부는 여럿이 함께 모여 춤을 추고 술을 마시는 나이트클럽의 특성상 사회적 거리 두기가 지켜지기 쉽지 않다고 보고 경제 재개 대상에서 유흥업소를 제외했다.\n  이에 따라 유흥업소들은 여전히 영업 방침에 제한을 받는다.\n  최근에는 영국에서 2차 확산이 본격화하며 또다시 엄격한 조치가 내려질 위기에 놓였다.\n  영국의 유흥업계는 코로나19 전부터 높은 임대료 문제 등으로 재정적 어려움을 겪고 있었는데, 코로나19가 유흥업 위기를 가속화한 셈이다.\n  나이트클럽 281평에 50명만 출입, “전기세도 안 나와”이런 이유로 영국의 심야 산업 협회(Night Time Industries Association)는 일부 지역의 추가 방역 지침에 강력하게 반대하고 있다.\n  이들은 이미 엄격한 방역 지침이 내려진 까닭에 온전한 영업이 불가능하다고 주장한다.\n  한 시간에 15번씩 공기를 순환하고, 영업시간을 단축하는 등 영업에 지장이 많다고 말한다.\n  이 가운데 출입 인원수 제한이 직격탄이 됐다.\n  영국과 미국에서 나이트클럽을 운영하는 케이란 닐리는 “현재의 방역 지침에 따르면 281평 클럽에 손님 50명만 출입할 수 있다”면서 “이렇게 운영하면 나이트클럽 한 달 전기세도 안 나온다”고 말했다.\n  또 손님 간 사회적 거리 두기를 관리하기 위해 보안요원을 추가 고용하면서 오히려 인건비는 늘었다고 덧붙였다.\n  미용업·운송업도 줄줄이 타격문제는 유흥업의 위기가 미용업·운송업으로 이어진다는 점이다.\n ",
		"passage_Cnt": 1247
	},
	"Annotation": {
		"summary1": "영국에서 코로나19 확산을 막기 위해 6개월간 이어진 봉쇄 조치로 인해 나이트클럽 60% 이상이 파산 위기에 놓였다.",
		"summary2": "영국에서 신종 코로나바이러스 감염증(코로나19) 2차 확산이 이어지고 있는 가운데 나이트클럽 60% 이상이 2개월 이내 파산할 위기에 놓였다고 파이낸션타임스(FT)가 19일 (현지시간) 보도했다. 코로나19 확산을 막기 위해 6개월간 이어진 봉쇄조치가 직격탄이 됐다는 분석이다.",
		"summary3": null,
		"summary_3_cnt": null
	}
}