{
	"Meta(Acqusition)": {
		"doc_id": "REPORT-news_r-20249",
		"doc_category": "REPORT",
		"doc_type": "news_r",
		"doc_name": "5200만명의 카톡 '무서운 시너지' 카카오 분기 매출 1조 눈앞",
		"author": "박민제",
		"publisher": "중앙일보",
		"publisher_year": "2020",
		"doc_origin": "중앙일보"
	},
	"Meta(Refine)": {
		"passage_id": "REPORT-news_r-20249-00001",
		"passage": " 월 5200만명이 쓰는 플랫폼 카카오톡의 힘이 카카오의 역대 최대 실적으로 이어졌다.\n  코로나19 확산 국면에도 전 부문 고른 성장세를 이어간 만큼 하반기도 기대해볼 만하다는 평가가 나온다.\n    카카오는 지난 2분기 매출 9529억원, 영업이익 978억원을 올렸다고 6일 공시했다.\n  전년 동기 대비 각각 30%, 142% 증가했으며 분기 기준 역대 최고치다.\n  매출은 13분기 연속, 영업이익은 6분기 연속 역대 최대 기록을 경신했다.\n  지금 추세대로라면 분기 매출 1조원 시대가 머지않았다는 전망도 나온다.\n  영업이익률은 10.\n 3%다.\n  여민수 카카오 공동대표는 이날 컨퍼런스콜에서 “그간 겪어보지 못했던 많은 변화에 적응해가며 치열하게 대응한 결과 6분기 연속 최대 이익을 달성할 수 있었다”고 말했다.\n    실적 상승의 원동력은 국내 최대 메신저 플랫폼 ‘카카오톡’이다.\n  2분기 카카오톡의 글로벌 이용자 수는 5213만명, 국내 이용자는 4550만명을 돌파했다.\n  출시 10년이 지났지만 여전히 성장 중이다.\n  수·발신 메시지량은 지난해 2분기보다 34% 증가했다.\n  각종 콘텐트를 이용할 수 있는 3번째 탭 ‘샵(#)탭’의 이용자 방문횟수도 1년 전보다 28% 이상 늘었다.\n  샵탭 뉴스 이용자도 역대 최대치를 경신했다.\n  카톡에서 메시지만 주고받는게 아니라 뉴스도 보고 검색도 하고, 스포츠 영상도 보는 ‘슈퍼 앱’으로 변모하고 있다는 의미다.\n  오동환 삼성증권 연구원은 “코로나19 와중에도 전 사업부가 고르게 매출 성장률을 유지했고 영업이익도 성장세가 지속됐다”며 “카카오톡이란 플랫폼이 수익을 내는 구간에 들어간 게 핵심”이라고 설명했다.\n     실적 상승을 직접 견인한 분야는 광고·전자 상거래(커머스) 사업을 담당하는 ‘톡비즈’ 부문이다.\n  지난해 선보인 카카오톡 채팅 목록 상단의 노출광고(톡보드)는 1년 사이 광고주 8500여 곳을 확보했다.\n  지난 6월에는 역대 월 최고 매출을 달성했다.\n  ‘선물하기’‘톡딜’ 등의 커머스 분야도 2분기 전체 거래액이 전년 동기 대비 57% 늘었다.\n  명품 화장품, 면역 관련 건강식품 등이 꾸준히 인기를 얻은 덕분이다.\n    콘텐트 분야에선 일본 최대 웹툰 플랫폼 ‘픽코마’의 선전이 두드러졌다.\n  카카오재팬 픽코마의 거래액은 전분기 대비 61% 성장했다.\n  지난 달에는 일본 구글플레이와 앱스토어에서 모두 비게임 부문 매출 1위로 올라섰다.\n ",
		"passage_Cnt": 1207
	},
	"Annotation": {
		"summary1": "코로나19 확산에도 불구하고 역대 최대 실적을 기록한 카카오 실적 상승의 원동력은 카카오톡이다.",
		"summary2": "코로나19 확산 국면에도 전 부문 고른 성장세를 이어간 만큼 하반기도 기대해볼 만하다는 평가가 나온다. 월 5200만명이 쓰는 플랫폼 카카오톡의 힘이 카카오의 역대 최대 실적으로 이어졌다. 실적 상승의 원동력은 국내 최대 메신저 플랫폼 ‘카카오톡’이다.",
		"summary3": null,
		"summary_3_cnt": null
	}
}