{
	"Meta(Acqusition)": {
		"doc_id": "REPORT-news_r-24368",
		"doc_category": "REPORT",
		"doc_type": "news_r",
		"doc_name": "뒤엉켜 춤판, 산행 뒤 술판…불안한 가을",
		"author": "김선영",
		"publisher": "중앙일보",
		"publisher_year": "2020",
		"doc_origin": "중앙일보"
	},
	"Meta(Refine)": {
		"passage_id": "REPORT-news_r-24368-00001",
		"passage": "2030 젊은층이 클럽 대신 ‘라운지바’로 몰려들고 있다.\n  일부는 대학 캠퍼스 잔디밭이나 포장마차로 향했다.\n  5060 중장년층은 집콕 대신 가을 산행에 대거 나섰다.\n  이들이 신종 코로나바이러스 감염증(코로나19) 방역 지침을 지키는 한 문제될 것이 없다.\n     하지만 여러 곳에서 사회적 거리두기 수칙을 위반해 주민과 마찰을 빚거나 신고를 받고 출동한 경찰과 합법과 불법의 경계선에서 숨바꼭질을 벌였다.\n  방역 전문가들이 “38일 만에 코로나19 확진자가 20일 두 자릿수로 줄었지만 여전히 안심할 단계는 아니다”고 입을 모으는 상황에서다.\n  이른바 ‘코로나 풍선효과’다.\n  ‘불토(불타는 토요일)’인 20일 오전 2시30분.\n  서울 강남구 논현동의 한 라운지바에 경찰이 출동했다.\n  바에서 600m 떨어진 인근 파출소에 “라운지바에서 사람이 잔뜩 몰려 춤춘다”는 신고가 접수된 직후였다.\n  이날 경찰이 출동한 건 오전 1시에 이어 두 번째였다.\n     이날 중앙일보가 제보받은 라운지바 영상에 따르면 해당 라운지바는 일반 클럽과 다를 바 없었다.\n  젊은 손님들이 빼곡히 모여 춤추고 음식과 술을 나눠 마셨다.\n  손님 약 500명이 일어선 채 밀집해 ‘사회적 거리두기’가 무색했다.\n  그들 중 절반 이상은 마스크를 쓰지 않고 있었다.\n     하지만 경찰이 도착하자 손님 대부분은 밖으로 빠져나갔고 클럽 음악은 꺼졌다.\n  경찰은 출동 직후 20분간 방문객의 신분증을 검사하고 업장 내부를 확인했으나 ‘떨어져 있으라’는 수준의 계도만 하고 돌아갔다.\n  경찰이 떠나자 일부 손님은 “경찰 갔대!”를 외치며 다시 업장으로 들어갔다.\n     이날 라운지바에 있었던 A씨(31·강남구)는 “갑자기 DJ가 사이렌을 한 번 틀더니 음악을 잔잔하게 바꿨다”며 “직원들은 돌아다니며 ‘마스크를 쓰라’고 알렸다”고 말했다.\n  그는 “입구 직원이 경찰을 보면 곧바로 안쪽에 신호를 주는 것 같았다”고 덧붙였다.\n   라운지바는 음악을 틀어놓고 술을 마시는 ‘일반음식점’이다.\n  춤추거나 노래할 수 없다.\n  사회적 거리두기 2단계 집합금지 대상에서 빠진 이유다.\n  강남구의 한 유흥주점 관계자는 “클럽이 문을 닫자 ‘클럽화’한 라운지바들이 입소문을 탔다”며 “이런 곳이 한두 개가 아니다”고 말했다.\n  그는 “클럽에서 일하던 DJ들도 라운지바로 옮겨왔다”며 “해당 라운지바의 경우 테이블 하나 가격이 500만원부터 시작했다”고 전했다.\n ",
		"passage_Cnt": 1211
	},
	"Annotation": {
		"summary1": "코로나19 방역 지침을 지키는 한 문제 될 것이 없지만 여러 곳에서 사회적 거리두기 수칙을 위반해 마찰을 빚고 있다.",
		"summary2": "이들이 신종 코로나바이러스 감염증(코로나19) 방역 지침을 지키는 한 문제될 것이 없다. 하지만 여러 곳에서 사회적 거리두기 수칙을 위반해 주민과 마찰을 빚거나 신고를 받고 출동한 경찰과 합법과 불법의 경계선에서 숨바꼭질을 벌였다.",
		"summary3": null,
		"summary_3_cnt": null
	}
}