{
	"Meta(Acqusition)": {
		"doc_id": "REPORT-news_r-05821",
		"doc_category": "REPORT",
		"doc_type": "news_r",
		"doc_name": "\"휴일·밤낮없다, 5분 대기조\"…'코로나 격무' 쓰러지는 공무원들",
		"author": "김기환",
		"publisher": "중앙일보",
		"publisher_year": "2020",
		"doc_origin": "중앙일보"
	},
	"Meta(Refine)": {
		"passage_id": "REPORT-news_r-05821-00001",
		"passage": "일명 ‘마스크 단속반’으로 불리는 식품의약품안전처 위해사범중앙조사단 소속 유명종 수사팀장은 지난달 24일 오후 8시 40분 서울 관악구 봉천동에서 “중국인들이 마스크를 대량으로 트럭에 옮겨싣고 있는데 수상하다”는 신고를 받았다.\n  곳곳에 나가 있던 단속반원이 현장에 도착한 시간은 오후 9시 10분.\n  이틀 뒤인 26일 밤엔 “역삼역 카페인데 옆 테이블에서 마스크 1000만장을 인천 남동공단에서 거래하는 계약을 맺고 있다”는 신고를 받았다.\n  단속반과 경찰 4개 조가 바로 남동공단으로 출동했다.\n  두 사건 모두 위법 행위가 있었는지 조사 중이다.\n  유 팀장과 동료들은 단속반이 출범한 지난달 5일부터 휴일ㆍ밤낮없이 이런 식으로 일해왔다.\n  신종 코로나바이러스 감염증(코로나 19)이 기승을 부리면서 최전선에서 일하는 공무원이 격무에 시달리고 있다.\n  질병관리본부나 대구ㆍ경북 지역을 중심으로 파견한 의료진과 보건 인력뿐 아니라 후방 곳곳에서 지원하는 공무원도 마찬가지다.\n  확진자와 직접 접촉할 위험도 많아 공무원 확진자만 현재까지 최소 10명 이상으로 파악됐다.\n  공무원 자가격리자도 급증하는 추세다.\n  지난달 28일 대구 달성군보건소 소속 공무원 A씨는 간호사와 함께 달성군 화원읍의 한 주택으로 출동했다.\n  확진 판정을 받은 20대 여성을 병원으로 옮기기 위해서다.\n  하지만 A씨가 집에서 자고 있던 그를 깨워 옮기는 과정에서 사달이 났다.\n  술에 취한 20대 여성이 앰뷸런스에서 자신을 내리려고 하는 A씨에게 “너도 걸려볼래”라며 얼굴에 침을 뱉었다.\n  A씨는 즉시 격리됐고, 검체 검사 결과 음성 판정을 받았다.\n  경찰은 20대 여성을 공무집행방해 혐의로 입건했다.\n  지난 1월 30일 우한 교민을 충북 진천 공무원 인재개발원과 충남 아산 경찰 인재개발원에 나눠 수용하는 과정에선 행정안전부 공무원들이 지역 주민 반발로 어려움을 겪었다.\n  교민 진입을 막기 위해 트랙터ㆍ지게차ㆍ경운기가 등장했다.\n  밤늦게까지 시위가 열린 시위를 막는 과정에서 멱살을 잡히고 물세례를 맞았다.\n  지난달 27일엔 전주시청 공무원 B씨가 자택에서 코피를 흘리며 의식을 잃고 쓰러진 채 발견됐다.\n  B씨 가족은 “주말 없이 일하다 오후 11시쯤 들어와 ‘요즘 비상 업무가 많아 힘들다’고 털어놓는 경우가 많았다”고 말했다.\n  B씨는 숨지기 전날도 신천지 교인 명단을 전수조사하느라 야근했다.\n  성주군청 공무원 C씨는 지난 2일 오전 11시 군청 화장실에서 쓰러진 채 발견됐다.\n ",
		"passage_Cnt": 1236
	},
	"Annotation": {
		"summary1": "코로나19가 기승을 부리면서 질병관리본부나 대구·경북 지역을 중심으로 파견한 의료진과 보건인력뿐 아니라 공무원이 격무에 시달리고 자가 격리자도 급증하고 있다.",
		"summary2": "신종 코로나바이러스 감염증(코로나 19)이 기승을 부리면서 최전선에서 일하는 공무원이 격무에 시달리고 있다. 질병관리본부나 대구ㆍ경북 지역을 중심으로 파견한 의료진과 보건 인력뿐 아니라 후방 곳곳에서 지원하는 공무원도 마찬가지다. 공무원 자가격리자도 급증하는 추세다.",
		"summary3": null,
		"summary_3_cnt": null
	}
}