{
	"Meta(Acqusition)": {
		"doc_id": "REPORT-news_r-21981",
		"doc_category": "REPORT",
		"doc_type": "news_r",
		"doc_name": "”등교 불안, 학원도 문닫아“ 스터디카페만 붐비는 수능 D-99",
		"author": "채혜선",
		"publisher": "중앙일보",
		"publisher_year": "2020",
		"doc_origin": "중앙일보"
	},
	"Meta(Refine)": {
		"passage_id": "REPORT-news_r-21981-00001",
		"passage": " “수능이 100일도 안 남았잖아요.\n  학교는 가지만 불안 불안해요.\n ” 서울 지역 고3 수험생 A양은 교육부가 수도권에서 고3을 빼고 전 학년 등교 중단 조처를 내린 데 대해 26일 이렇게 말했다.\n  자칫 등교했다가 학교 내 신종 코로나바이러스 감염증(코로나19) 감염이 우려된다는 것이다.\n  이날로 대학수학능력시험(수능)은 99일 앞으로 다가왔다.\n  A양은 “코로나19 재유행 상황에서 입시까지 얼마 남지 않아 공부에 집중이 어렵다”고 말했다.\n  그가 최근 작성한 스터디 플래너에는 “기상이 힘들다” “슬럼프가 왔다”는 말이 적혀 있었다.\n    수능 제때 볼 수 있을까…고3 불안   코로나19 확산세에 고3 수험생들의 불안감이 더욱 커지고 있다.\n  우선 등교가 미뤄졌던 것처럼 수능 일정에 변동이 생길까 걱정하는 목소리가 컸다.\n  고3 B군은 “코로나19로 수능이 미뤄지진 않을지 나 포함 주변 친구들이 고민에 빠졌다”고 말했다.\n   그동안 독서실을 자습 공간으로 삼았던 고3 C양은 최근 코로나19 재확산 조짐에 공부하러 갈 곳이 없다고 했다.\n  C양은 “코로나19 사태 초반에는 동네에 확진자가 많이 안 나와 독서실을 다녔었다”며 “하지만 최근 확진자가 늘며 독서실을 무서워서 가지 못하게 됐다”고 말했다.\n  이어 “독서실에서 주로 공부했던 친구들도 이젠 독서실을 가지 않는다”며 “수능이 다가오면서 공부는 손에 잡히질 않는데, 코로나19 때문에 불안함만 더욱 커진다”고 덧붙였다.\n    이 와중에 붐비는 스터디 카페 스터디 카페를 찾는 수험생도 늘고 있다.\n  코로나19 확산 우려로 대형학원·도서관 등 자습공간이 마련된 다중이용시설의 운영이 중단되면서 학생이 몰리는 것으로 보인다.\n  이날 한 스터디 카페 앞에서 만난 재수생은 “(공부하러) 갈 데가 없다.\n  도서관은 문을 닫았고 카페는 불안하니 스터디 카페를 찾았다”고 말했다.\n   이날 오후 경기도 성남 분당의 학원가에 위치한 한 스터디 카페엔 40개 좌석 중 35개가 차 있었다.\n  여러 명이 모여 앉는 대형 책상에 자리를 잡은 3명은 마스크를 전부 쓰고 있었다.\n  창가에 자리한 공개형 좌석에 앉은 5명도 모두 마스크를 착용했다.\n  이 같은 모습은 칸막이가 있는 1인형 좌석으로 가면 달라졌다.\n  총 18석이 마련된 1인형 좌석들은 만석이었다.\n   이중엔 마스크를 턱밑으로 내리고 공부하거나 아예 쓰지 않은 학생들이 군데군데 눈에 띄었다.\n ",
		"passage_Cnt": 1203
	},
	"Annotation": {
		"summary1": "대학수학능력시험을 앞둔 고3 수험생 A 양은 코로나19의 감염이 우려된다고 말했다.",
		"summary2": "자칫 등교했다가 학교 내 신종 코로나바이러스 감염증(코로나19) 감염이 우려된다는 것이다. 이날로 대학수학능력시험(수능)은 99일 앞으로 다가왔다. “수능이 100일도 안 남았잖아요. 학교는 가지만 불안 불안해요. ” 서울 지역 고3 수험생 A양은 교육부가 수도권에서 고3을 빼고 전 학년 등교 중단 조처를 내린 데 대해 26일 이렇게 말했다.",
		"summary3": null,
		"summary_3_cnt": null
	}
}