{
	"Meta(Acqusition)": {
		"doc_id": "REPORT-news_r-16547",
		"doc_category": "REPORT",
		"doc_type": "news_r",
		"doc_name": "시민단체 \"보존식 없었다\"…‘햄버거병' 안산유치원 검찰 고발",
		"author": "심석용",
		"publisher": "중앙일보",
		"publisher_year": "2020",
		"doc_origin": "중앙일보"
	},
	"Meta(Refine)": {
		"passage_id": "REPORT-news_r-16547-00001",
		"passage": " 집단 식중독이 발생한 경기도 안산 유치원에서 일명 햄버거병으로 불리는 용혈성요독증후군(HUS) 환자가 늘어나는 가운데 해당 유치원이 고발됐다.\n  시민단체 정치하는엄마들은 업무상과실치상 및 식품위생법 위반 혐의로 안산 A 유치원을 수원지검 안산지청에 고발했다고 27일 밝혔다.\n  정치하는 엄마들은 해당 유치원이 건강을 해칠 우려가 있는 식품을 피해 아동에게 섭취케 해 장 출혈성 대장균에 의한 질병 또는 용혈성요독증후군의 상해를 입혔다고 주장했다.\n  이 단체는 고발장에 “A 유치원이 사태의 직접적 원인으로 강하게 의심되는 지난 10~15일까지의 급식을 보존하지 않았다”며 “장 출혈성 대장균은 주로 덜 익은 소고기에서 발생하는 경향이 있는데, 식단 확인 결과 지난 12일에 소고기 불고기가 포함되어 있었다”고 적었다.\n  식품위생법 제88조에 따르면 집단급식소의 경우, 조리·제공한 식품의 매회 1인분 분량을 144시간(만6일) 이상 보관하도록 규정한다.\n  그러나 해당 유치원은 음식 6건을 보존 조치하지 않은 것으로 나타났다.\n  정치하는엄마들의 장하나 활동가는 “보존식이 없어 보건당국이 역학조사에 난항을 겪고 있으므로 검찰이 강제수사를 포함한 실질적인 수단으로 식자재 납품업체의 장부, 조리 매뉴얼 등 자료를 조속히 확보하고 인적조사를 해야 한다”고 밝혔다.\n  학부모 “유치원 법적 조치 등 검토”A유치원 학부모들도 유치원에 책임을 묻기 위해 법적 조치 등 여러 방안을 검토 중이다.\n  지난 26일 오후 열린 학부모 비상회의에 동석한 황다연 법무법인 혜 변호사는 “이번 사태 원인을 밝히기 위해서는 납품 업체를 통해 아이들이 먹은 음식 및 식재료를 모두 조사할 필요가 있다”고 말했다.\n  황 변호사는 과거 ‘한국맥도날드 햄버거병 국가배상청구소송’의 법률대리인을 맡았다.\n   지난 25일 자신을 A 유치원에 다니는 5살 아이의 엄마라고 밝힌 작성자는 청와대 국민청원 게시판에 ‘햄버거병 유발시킨 2년 전에도 비리 감사 걸린 유치원’이라는 제목의 글을 올렸다.\n  그는 “식중독 증상을 호소하는 원생들이 늘기 시작했는데, 이 유치원은 아파트 앞에서 주마다 열리는 장날 음식을 의심했다”라며 “이 유치원은 18년도에도 교육과 무관한 개인경비로 사용해 감사에 걸렸다.\n  이런 유치원이 과연 이번에도 제대로 된 음식을 먹였을까”며 문제를 제기했다.\n  2017년 경기도 교육청 사립유치원 감사 결과에 따르면 당시 A 유치원 원장은 교비 부정 사용, 부실회계처리 등 이유로 정직 3개월 처분을 받았다.\n ",
		"passage_Cnt": 1241
	},
	"Annotation": {
		"summary1": "집단 식중독이 발생한 경기도 유치원에서 용혈성요독증후군 환자가 늘어가는 가운데 시민단체가 업무상과실치상 및 식품위생법 위반 혐의로 수원지검 안산지청에 유치원을 고발했다.",
		"summary2": "집단 식중독이 발생한 경기도 안산 유치원에서 일명 햄버거병으로 불리는 용혈성요독증후군(HUS) 환자가 늘어나는 가운데 해당 유치원이 고발됐다. 시민단체 정치하는엄마들은 업무상과실치상 및 식품위생법 위반 혐의로 안산 A 유치원을 수원지검 안산지청에 고발했다고 27일 밝혔다.",
		"summary3": null,
		"summary_3_cnt": null
	}
}