{
	"Meta(Acqusition)": {
		"doc_id": "REPORT-news_r-23920",
		"doc_category": "REPORT",
		"doc_type": "news_r",
		"doc_name": "음원차트 점령한 웹툰 OST…인기 웹툰IP, 오디오 시장도 넘본다",
		"author": "정원엽",
		"publisher": "중앙일보",
		"publisher_year": "2020",
		"doc_origin": "중앙일보"
	},
	"Meta(Refine)": {
		"passage_id": "REPORT-news_r-23920-00001",
		"passage": " 카카오와 네이버의 웹툰 콘텐트가 애니메이션·드라마·영화를 넘어 음원시장까지 영향력을 넓히고 있다.\n  카카오페이지의 사내독립기업 다음 웹툰에서 누적 2억 2000만 조회수를 달성한 웹툰 '취향저격 그녀(작가 로즈옹)'의 오리지널사운드트랙(OST) 6곡이 최근 음원차트 상위권을 점령했다.\n  해당 OST는 지난 11일 기준 멜론 음원차트 10위 이내에 4곡이 이름을 올렸다.\n  카카오·네이버가 뛰어드는 웹툰 OST 카카오페이지는 지난 1월 웹소설 달빛조각사의 OST를 가수 이승철과 함께 선보인 데 이어, 3월엔 래퍼 비와이와 함께 이태원클라쓰 OST를 내놨다.\n  해당 음원은 원작의 인기와 유명 가수의 협업으로 주목을 받고, 음원 차트에도 진입했다.\n  7월부터 연달아 선보인 취향저격 그녀 OST는 '취기를 빌려'(그룹 B1A4의 산들)가 발매 후 두 달간 상위 10위 안에 이름을 올리며 현재(15일)도 음원차트 2위를 기록하는 중.\n  네이버도 지난 6월엔 웹툰 '남과 여'(혀노 작가)를 오디오 드라마로 진화시키며 국내 최초로 '오디오 시네마'를 선보였다.\n  해당 프로젝트엔 곽진언 등 가수 13팀이 OST 14곡 제작에 참여했다.\n  웹툰을 듣는 콘텐트로 전환하며 음원까지 내놓은 것.\n  글로벌 애니메이션으로 제작한 갓오브하이스쿨, 노블레스 등의  OST에도 김재중 등 인기 가수가 참여할 예정이다.\n   웹툰 산업 한 축으로 부상2000년대 후반 웹툰에도 백그라운드 음악(BGM) 형태로 음원이 있었다.\n  2010년 네이버 웹툰 '구름의 노래'(호랑 작가) OST가 정식 앨범으로 나왔었다.\n  당시엔 웹툰 작가의 인맥을 통해 홍대 인디 가수 등이 음원을 출시한 경우가 많았다.\n   최근엔 다르다.\n  네이버·카카오 등 대형 콘텐트 플랫폼을 중심으로 산업이 커지면서 웹툰 OST도 콘텐트 상품의 한 축이 됐다.\n  특히 인기 웹툰에 인기 가수의 음원을 결합해 협업(콜라보레이션)하는 모델은 검증된 성공 방정식이 되고 있다.\n   서찬휘 만화칼럼리스트는 \"웹툰이 플랫폼 중심으로 완전히 자리 잡으며 영상·음원 등을 철저히 기획하는 산업형태의 모습이 보인다\"며 \"올해 초 달빛조각사나 이태원클라쓰 OST를 기점으로 웹툰 OST 위상이 올라갔다\"고 설명했다.\n  웹툰 IP의 다각화웹툰 지식재산권(IP) 시장은 올해 1조원을 돌파할 전망이다.\n  KT 경제경영연구소에 2014년 2100억 원대에 비하면 4.\n 8배 가량 커졌다.\n ",
		"passage_Cnt": 1205
	},
	"Annotation": {
		"summary1": "플랫폼 중심으로 완전히 자리 잡아 철저한 기획하에 산업 형태가 된 웹툰은 지적재산권 시장에 1조 원 돌파를 앞두고 있다.",
		"summary2": "서찬휘 만화칼럼리스트는 \"웹툰이 플랫폼 중심으로 완전히 자리 잡으며 영상·음원 등을 철저히 기획하는 산업형태의 모습이 보인다\"며 \"올해 초 달빛조각사나 이태원클라쓰 OST를 기점으로 웹툰 OST 위상이 올라갔다\"고 설명했다. 웹툰 지식재산권(IP) 시장은 올해 1조원을 돌파할 전망이다.",
		"summary3": null,
		"summary_3_cnt": null
	}
}