{
	"Meta(Acqusition)": {
		"doc_id": "REPORT-news_r-00749",
		"doc_category": "REPORT",
		"doc_type": "news_r",
		"doc_name": "북극곰 '소환'해 재롱보는 증강현실(AR)동물원 가보니  ",
		"author": "박진호",
		"publisher": "중앙일보",
		"publisher_year": "2020",
		"doc_origin": "중앙일보"
	},
	"Meta(Refine)": {
		"passage_id": "REPORT-news_r-00749-00001",
		"passage": " “늘리니까 커지네! 우와 신기하다.\n  너무 커.\n  다시 작게….\n ” 지난 9일 오후 강원도 춘천시 서면 애니메이션박물관.\n  스마트폰을 든 관광객이 ‘Jump AR’ 앱을 실행한 뒤 동물을 소환하자 SF영화처럼 바닥에서 섬광이 일어나더니 비룡이 땅을 박차고 날아올랐다.\n  화면을 터치하자 비룡이 불을 뿜기 시작했고 스마트폰을 보던 관광객들은 ‘우와’하고 탄성이 질렀다.\n  옆으로 이동해 다른 동물을 소환하자 작은 크기의 북극곰이 화면에 나타났다.\n  화면을 늘리자 북극곰 크기가 화면을 다 덮을 만큼 커졌다.\n  소환된 북극곰은 서서 걷기도 하고 소리를 내며 재롱을 부리기도 했다.\n    딸과 함께 AR 동물원을 찾은 안상미(34·여·강원 춘천시)씨는“요즘 딸이 스노우 앱에 있는 AR 캐릭터를 엄청 좋아해 인터넷에서 보고 찾아왔는데 아이가 재밌어해 기분이 좋다”고 말했다.\n  옆에 있던 딸 이서윤(6)양은 “캐릭터들이 다 너무 귀엽다.\n  그중에 북극곰이 가장 마음에 든다”고 했다.\n  동물 크기 위치도 바꿔가며 감상할 수 있어춘천애니메이션박물관과 SK텔레콤이 박물관 야외 정원에 AR(증강현실) 동물원을 열었다.\n  7260㎡ 규모의 이 동물원은 SK텔레콤의 최신 기술력이 집약돼 동물을 실제로 눈앞에서 보는 것과 같은 즐거움을 느낄 수 있다.\n  ‘초실감 렌더링(Hyper Realistic Rendering)’ 기술과 ‘환경반영 렌더링(Environmental Rendering)’ 기술을 통해 초고화질 시각효과도 구현했다.\n    최신 기술 적용으로 동물마다 털이 세밀하게 구현돼 있고 사용자가 이동해 동물의 옆모습과 뒷모습 등도 볼 수 있다.\n  동물의 크기나 위치도 조정이 가능하다.\n  특히 스마트폰 화면 속 동물을 터치하면 다양한 반응도 나온다.\n  또 빛에 따라 동물이 반응하기 때문에 불이 갑자기 밝아지면 동물이 깜짝 놀라기도 한다.\n  현재 소환 가능한 동물은 북극곰, 나무늘보, 자이언트 캣, 웰시코기, 알파카, 비룡, 아기비룡, 레서판다, 고양이, 판다 등 총 10종이다.\n  소환한 동물과 함께 사진과 동영상을 촬영할 수 있고 찍은 사진과 영상은 소셜네트워크서비스(SNS)를 통해 공유할 수도 있다.\n    스마트폰만 있으면 누구나 쉽게 동물 소환가족과 함께 AR 동물원을 찾은 이정수(36·강원 춘천시)씨는 “스마트폰만 있으면 쉽게 동물을 소환할 수 있어 신기하다”며 “포켓몬 잡는 것과 비슷해 아이들도 좋아하는 것 같다”고 말했다.\n ",
		"passage_Cnt": 1221
	},
	"Annotation": {
		"summary1": "춘천시 AR동물원에서는 스마트폰만 있으면 Jump AR 앱에서 동물을 소환할 수 있다. ",
		"summary2": "“늘리니까 커지네! 우와 신기하다. 너무 커. 다시 작게…. ” 지난 9일 오후 강원도 춘천시 서면 애니메이션박물관. 스마트폰을 든 관광객이 ‘Jump AR’ 앱을 실행한 뒤 동물을 소환하자 SF영화처럼 바닥에서 섬광이 일어나더니 비룡이 땅을 박차고 날아올랐다. 가족과 함께 AR 동물원을 찾은 이정수(36·강원 춘천시)씨는 “스마트폰만 있으면 쉽게 동물을 소환할 수 있어 신기하다”며 “포켓몬 잡는 것과 비슷해 아이들도 좋아하는 것 같다”고 말했다.",
		"summary3": null,
		"summary_3_cnt": null
	}
}