{
	"Meta(Acqusition)": {
		"doc_id": "REPORT-news_r-05296",
		"doc_category": "REPORT",
		"doc_type": "news_r",
		"doc_name": "“이태원 우리가 씹어먹는 겁니다” 드라마도 접수한 괴물 신인 ",
		"author": "민경원",
		"publisher": "중앙일보",
		"publisher_year": "2020",
		"doc_origin": "중앙일보"
	},
	"Meta(Refine)": {
		"passage_id": "REPORT-news_r-05296-00002",
		"passage": " 전과자인 사장님과 재벌가 서자인 친구를 비롯해 트랜스젠더를 꿈꾸는 주방장, 외국인처럼 보이는 아르바이트생 등 세상의 편견에서 자유롭지 못한 사람들과 부딪히면서 감정이 무엇인지를 알아가는 것.\n  방송을 보면서 나 역시 소시오패스는 아닐지언정 편협한 사고방식은 별반 다르지 않았구나 하며 반성하는 시청자들이 한둘이 아니지 않을까.\n    캐릭터 간의 연관성도 극에 대한 몰입도를 높인다.\n  전혀 다른 상황에 처해 있지만 서로 닮은 구석을 알아보면서 관계가 한층 복잡해지는 것.\n  극 중 오수아(권나라)는 조이서에 대해 “눈치가 빠르고 상황판단이 빠르다”고 평한다.\n  이를 들은 장가의 장대희 회장(유재명)은 “내가 자넬 그렇게 보고 있다”며 흥미로워하는 식이다.\n  장 회장은 조이서를 두고 “나와 같은 색”이라 칭하고, 박새로이는 장근수(김동희)에게 “너한테서 나를 봤다”고 말한다.\n  각각의 케미가 빛을 발하면서 극은 더욱 탄탄해진다.\n  서로를 끌어당기는 점성이 강해지면서 밀도를 높이는 덕분이다.\n  어쩌면 서로 닮았기에 그 결핍 혹은 과잉을 한눈에 알아봤을는지도 모른다.\n    더욱 놀라운 것은 이번이 김다미의 첫 드라마 도전이라는 점이다.\n  독립영화 ‘2017 동명이인 프로젝트’를 제외하면 영화 ‘나를 기억해’(2018)와 ‘마녀’(2018)가 필모그래피의 전부다.\n  인천대 공연예술학과 4학년 때 1500대 1의 경쟁률을 뚫고 ‘마녀’에 합류하면서 그해 대종상ㆍ청룡상 등 신인상을 휩쓴 ‘괴물 신인’으로 떠올랐다.\n  DNA 조작으로 탄생한 초능력 소녀 자윤 역을 맡아 순진함과 살벌함을 오가는 섬뜩한 연기를 펼쳤다.\n  3개월 동안 하루 3~4시간씩 투자한 액션 연기도 빛을 발했다.\n  당초 ‘마녀’를 시리즈로 기획한 박훈정 감독은 내년 속편 개봉을 목표로 준비 중이다.\n  김다미 역시 시리즈로 계약한 상태다.\n    어릴 적부터 배우를 꿈꿨던 그는 “연기를 하기엔 스스로 준비가 안 됐다고 여겨 대학 입학 후 3년간 연극 워크숍 공연에만 매진했다”고 했다.\n  그동안 응축해온 에너지를 폭발시키고 있는 것이다.\n  “여전히 어렵고 고민되고 부족한 부분이 너무 많지만 성장해 나가는 과정이니 최대한 즐기면서 하자는 마음”이라니 앞으로 어디로 튈지 차마 예측하지도 못하겠다.\n  선과 악이 공존하는 얼굴 사이로 일상에서 쌓아온 감정을 켜켜이 채워 넣다 보면 또다시 한국 영화 혹은 드라마에서 한 번도 본 적 없는 캐릭터가 탄생하지 않을까.\n ",
		"passage_Cnt": 1216
	},
	"Annotation": {
		"summary1": "괴물 신인으로 떠올랐던 김 씨는 독립영화 2017 동명이안 프로젝트를 제외하면 영화 나를 기억해와 마녀가 그녀의 필모그래피의 전부이다. ",
		"summary2": null,
		"summary3": "더욱 놀라운 것은 이번이 김다미의 첫 드라마 도전이라는 점이다. 독립영화 ‘2017 동명이인 프로젝트’를 제외하면 영화 ‘나를 기억해’(2018)와 ‘마녀’(2018)가 필모그래피의 전부다. 인천대 공연예술학과 4학년 때 1500대 1의 경쟁률을 뚫고 ‘마녀’에 합류하면서 그해 대종상ㆍ청룡상 등 신인상을 휩쓴 ‘괴물 신인’으로 떠올랐다.",
		"summary_3_cnt": 191
	}
}